prodigal-1.0.2.dist-info/WHEEL
prodigal-1.0.2.dist-info/RECORD
prodigal-1.0.2.dist-info/METADATA
prodigal/prodigal_py.cpython-310-x86_64-linux-gnu.so
