Metadata-Version: 2.1
Name: prodigal
Version: 1.0.2
Summary: Python binding for Prodigal command tool.
Requires-Python: <3.11,>=3.10
